MANIFEST.in
README.md
setup.py
aliyun_exporter/QueryMetricMetaRequest.py
aliyun_exporter/QueryProjectMetaRequest.py
aliyun_exporter/__init__.py
aliyun_exporter/__main__.py
aliyun_exporter/collector.py
aliyun_exporter/info_provider.py
aliyun_exporter/test_utils.py
aliyun_exporter/utils.py
aliyun_exporter/web.py
aliyun_exporter/static/style.css
aliyun_exporter/templates/detail.html
aliyun_exporter/templates/error.html
aliyun_exporter/templates/index.html
aliyun_exporter/templates/yaml.html
aliyun_exporter_czb.egg-info/PKG-INFO
aliyun_exporter_czb.egg-info/SOURCES.txt
aliyun_exporter_czb.egg-info/dependency_links.txt
aliyun_exporter_czb.egg-info/entry_points.txt
aliyun_exporter_czb.egg-info/not-zip-safe
aliyun_exporter_czb.egg-info/requires.txt
aliyun_exporter_czb.egg-info/top_level.txt