Metadata-Version: 2.1
Name: aliyun-exporter-czb
Version: 0.3.1
Summary: Alibaba Cloud CloudMonitor Prometheus exporter
Home-page: https://github.com/hanyunfeng6163/aliyun-exporter
Author: Aylei Wu
Author-email: rayingecho@gmail.com
License: Apache 2.0
Keywords: monitoring prometheus exporter aliyun alibaba cloudmonitor
Platform: UNKNOWN
Classifier: Intended Audience :: Developers
Classifier: Intended Audience :: System Administrators
Classifier: Topic :: System :: Monitoring
Classifier: License :: OSI Approved :: Apache Software License
Classifier: Programming Language :: Python :: 3
Classifier: Programming Language :: Python :: 3.7
